shai_plugin-0.5.1.dist-info/METADATA
shai_plugin-0.5.1.dist-info/WHEEL
shai_plugin-0.5.1.dist-info/entry_points.txt
shai_plugin-0.5.1.dist-info/licenses/LICENSE
shai_plugin/__init__.py
shai_plugin/cli.py
shai_plugin/commands/__init__.py
shai_plugin/commands/generate_docs.py
shai_plugin/config/__init__.py
shai_plugin/config/config.py
shai_plugin/config/integration_config.py
shai_plugin/config/logger_format.py
shai_plugin/core/__init__.py
shai_plugin/core/documentation/__init__.py
shai_plugin/core/documentation/generator.py
shai_plugin/core/documentation/schema_doc.py
shai_plugin/core/entities/__init__.py
shai_plugin/core/entities/invocation.py
shai_plugin/core/entities/message.py
shai_plugin/core/entities/plugin/__init__.py
shai_plugin/core/entities/plugin/io.py
shai_plugin/core/entities/plugin/parameter_type.py
shai_plugin/core/entities/plugin/request.py
shai_plugin/core/entities/plugin/setup.py
shai_plugin/core/model_factory.py
shai_plugin/core/plugin_executor.py
shai_plugin/core/plugin_registration.py
shai_plugin/core/runtime.py
shai_plugin/core/server/__base/__init__.py
shai_plugin/core/server/__base/filter_reader.py
shai_plugin/core/server/__base/request_reader.py
shai_plugin/core/server/__base/response_writer.py
shai_plugin/core/server/__base/writer_entities.py
shai_plugin/core/server/__init__.py
shai_plugin/core/server/io_server.py
shai_plugin/core/server/router.py
shai_plugin/core/server/serverless/__init__.py
shai_plugin/core/server/serverless/request_reader.py
shai_plugin/core/server/serverless/response_writer.py
shai_plugin/core/server/stdio/__init__.py
shai_plugin/core/server/stdio/request_reader.py
shai_plugin/core/server/stdio/response_writer.py
shai_plugin/core/server/tcp/__init__.py
shai_plugin/core/server/tcp/request_reader.py
shai_plugin/core/utils/__init__.py
shai_plugin/core/utils/class_loader.py
shai_plugin/core/utils/http_parser.py
shai_plugin/core/utils/position_helper.py
shai_plugin/core/utils/yaml_loader.py
shai_plugin/entities/__init__.py
shai_plugin/entities/agent.py
shai_plugin/entities/datasource.py
shai_plugin/entities/datasource_manifest.py
shai_plugin/entities/endpoint.py
shai_plugin-0.5.1.dist-info/RECORD
